ramtorch/__init__.py
ramtorch/helpers.py
ramtorch/zero1.py
ramtorch/zero2.py
ramtorch/modules/__init__.py
ramtorch/modules/linear.py
ramtorch/stochastic_optimizers/__init__.py
ramtorch/stochastic_optimizers/adamw.py
ramtorch-0.2.2.dist-info/licenses/LICENSE
ramtorch-0.2.2.dist-info/METADATA
ramtorch-0.2.2.dist-info/WHEEL
ramtorch-0.2.2.dist-info/top_level.txt
ramtorch-0.2.2.dist-info/RECORD
