Metadata-Version: 2.4
Name: RamTorch
Version: 0.2.2
Summary: RAM is All You Need
Author-email: Lodestone <lodestone.rock@gmail.com>
License: Apache-2.0
Project-URL: Homepage, https://github.com/lodestone-rock/RamTorch
Classifier: Programming Language :: Python :: 3
Classifier: Operating System :: OS Independent
Requires-Python: >=3.8
License-File: LICENSE
Dynamic: license-file
